[
  {
    "id": "614f7241fe86ed248dfc892a",
    "salary": "$1,138.03",
    "image": "https://randomname.de/images/twitter_enjoythetau.jpg",
    "age": 38,
    "name": "Meyers Spence",
    "gender": "male",
    "company": "GENMOM",
    "email": "meyersspence@genmom.com",
    "phone": "+1 (801) 418-3838"
  },
  {
    "id": "614f7241213a2c0158fea7ec",
    "salary": "$1,618.91",
    "image": "https://randomname.de/images/twitter_vitorfelixs.jpg",
    "age": 24,
    "name": "Evangeline Matthews",
    "gender": "female",
    "company": "INTERLOO",
    "email": "evangelinematthews@interloo.com",
    "phone": "+1 (845) 468-2910"
  },
  {
    "id": "614f7241320f98434c932399",
    "salary": "$2,208.90",
    "image": "https://randomname.de/images/twitter_bhargavik.jpg",
    "age": 21,
    "name": "Valentine Heath",
    "gender": "male",
    "company": "OLUCORE",
    "email": "valentineheath@olucore.com",
    "phone": "+1 (965) 406-2994"
  },
  {
    "id": "614f72411d47e7a75c10f730",
    "salary": "$3,299.87",
    "image": "https://randomname.de/images/twitter_kiandavoodi.jpg",
    "age": 29,
    "name": "Small Sykes",
    "gender": "male",
    "company": "YOGASM",
    "email": "smallsykes@yogasm.com",
    "phone": "+1 (935) 554-2232"
  },
  {
    "id": "614f7241cafbee828d1f3e53",
    "salary": "$2,279.95",
    "image": "https://randomname.de/images/twitter_odeskfreelancer.jpg",
    "age": 32,
    "name": "Hardy Singleton",
    "gender": "male",
    "company": "ATOMICA",
    "email": "hardysingleton@atomica.com",
    "phone": "+1 (858) 567-3995"
  },
  {
    "id": "614f7241de80a23169344860",
    "salary": "$2,061.24",
    "image": "https://randomname.de/images/twitter_katiefritz.jpg",
    "age": 28,
    "name": "Castaneda Deleon",
    "gender": "male",
    "company": "GEEKOLOGY",
    "email": "castanedadeleon@geekology.com",
    "phone": "+1 (856) 401-2991"
  },
  {
    "id": "614f72411f4f3a0ed9e1af03",
    "salary": "$2,048.43",
    "image": "https://randomname.de/images/twitter_mariamovan.jpg",
    "age": 21,
    "name": "Clayton Rosa",
    "gender": "male",
    "company": "GLUKGLUK",
    "email": "claytonrosa@glukgluk.com",
    "phone": "+1 (914) 467-3637"
  },
  {
    "id": "614f72419e338631c659b7eb",
    "salary": "$1,650.80",
    "image": "https://randomname.de/images/twitter_yoelzea.jpg",
    "age": 25,
    "name": "Jackson Lott",
    "gender": "male",
    "company": "BALOOBA",
    "email": "jacksonlott@balooba.com",
    "phone": "+1 (828) 418-2003"
  },
  {
    "id": "614f7241f759059f5493495e",
    "salary": "$2,193.16",
    "image": "https://randomname.de/images/twitter_kwastell.jpg",
    "age": 37,
    "name": "Little Merritt",
    "gender": "male",
    "company": "GEEKULAR",
    "email": "littlemerritt@geekular.com",
    "phone": "+1 (957) 534-2100"
  },
  {
    "id": "614f7241c75f3825eecb5f1c",
    "salary": "$1,576.64",
    "image": "https://randomname.de/images/twitter_ashtonsnook.jpg",
    "age": 29,
    "name": "Cunningham Lyons",
    "gender": "male",
    "company": "TELPOD",
    "email": "cunninghamlyons@telpod.com",
    "phone": "+1 (840) 506-3159"
  },
  {
    "id": "614f72415a56fe4dada81656",
    "salary": "$3,705.74",
    "image": "https://randomname.de/images/twitter_sam_potts.jpg",
    "age": 25,
    "name": "Kara Marks",
    "gender": "female",
    "company": "STREZZO",
    "email": "karamarks@strezzo.com",
    "phone": "+1 (889) 521-3162"
  },
  {
    "id": "614f724165bf2f02ac58122c",
    "salary": "$3,159.14",
    "image": "https://randomname.de/images/twitter_nskupova.jpg",
    "age": 31,
    "name": "Roseann Peterson",
    "gender": "female",
    "company": "COFINE",
    "email": "roseannpeterson@cofine.com",
    "phone": "+1 (919) 544-2374"
  },
  {
    "id": "614f72417dcf539d74369b49",
    "salary": "$3,644.24",
    "image": "https://randomname.de/images/twitter_katiefritz.jpg",
    "age": 31,
    "name": "Jeannette Finley",
    "gender": "female",
    "company": "AEORA",
    "email": "jeannettefinley@aeora.com",
    "phone": "+1 (949) 546-2386"
  },
  {
    "id": "614f72413d1133127c46a360",
    "salary": "$1,473.09",
    "image": "https://randomname.de/images/twitter_eugeneeweb.jpg",
    "age": 21,
    "name": "Riddle Gibbs",
    "gender": "male",
    "company": "ZOINAGE",
    "email": "riddlegibbs@zoinage.com",
    "phone": "+1 (890) 516-3245"
  },
  {
    "id": "614f72413d11334327c46a360",
    "salary": "$1,473.09",
    "image": "https://randomname.de/images/twitter_springfels.jpg",
    "age": 21,
    "name": "Riddle Gibbs",
    "gender": "male",
    "company": "ZOINAGE",
    "email": "riddlegibbs@zoinage.com",
    "phone": "+1 (890) 516-3245"
  }
]
